surveyeval/__init__.py
surveyeval/core_evaluation_lenses.py
surveyeval/evaluation_engine.py
surveyeval/html_tools.py
surveyeval/survey_parser.py
surveyeval/resources/EmptyForm.xlsx
surveyeval-0.1.31.dist-info/LICENSE
surveyeval-0.1.31.dist-info/METADATA
surveyeval-0.1.31.dist-info/WHEEL
surveyeval-0.1.31.dist-info/top_level.txt
surveyeval-0.1.31.dist-info/RECORD
