Metadata-Version: 2.1
Name: surveyeval
Version: 0.1.31
Summary: A toolkit for survey evaluation
Home-page: https://github.com/higherbar-ai/survey-eval
Author: Christopher Robert
Author-email: crobert@higherbar.ai
License: Apache 2.0
Project-URL: Documentation, https://surveyeval.readthedocs.io/
Requires-Python: >=3.10
License-File: LICENSE
Requires-Dist: pydantic
Requires-Dist: overrides <8.0.0,>=7.3.1
Requires-Dist: py-ai-workflows <1.0.0,>=0.31.0
Provides-Extra: parser
Requires-Dist: openpyxl <4.0.0,>=3.0.9 ; extra == 'parser'
Requires-Dist: py-ai-workflows[docs] <1.0.0,>=0.31.0 ; extra == 'parser'
